libstruct.py
libstruct-0.0.5.dist-info/LICENSE
libstruct-0.0.5.dist-info/METADATA
libstruct-0.0.5.dist-info/WHEEL
libstruct-0.0.5.dist-info/entry_points.txt
libstruct-0.0.5.dist-info/RECORD
