Metadata-Version: 2.3
Name: libstruct
Version: 0.0.5
Summary: Wrapper for struct module to simplify binary data
License: MIT
Author: Chuck Bass
Author-email: chuck@arcocad.net
Maintainer: Chuck Bass
Maintainer-email: chuck@arcocad.net
Requires-Python: >=3.12
Classifier: Development Status :: 3 - Alpha
Classifier: Intended Audience :: Developers
Classifier: Programming Language :: Python :: 3.12
Requires-Dist: hexout (>=0.5.0)
Project-URL: Homepage, https://github.com/hucker233/libstruct
